tutorial1/mine.v
// Verilog model of circuit of Figure 3.35 in Digital Systems 5th ed.

module oneadder(a,b,c,s,cout);
 input a,b,c;
 output s,cout;
 xor #1
 g1(w1, a, b),
 g2(s, w1, c);
 and #1
 g3(w2, c, b),
 g4(w3, c, a),
 g5(w4, a, b);
 or #1
 g6(cout, w2, w3, w4);
endmodule

module mine(x,y,s,cout,cin);
input [3:0] x,y;
output [3:0] s;
input cin;
output cout;
wire c[3:0];
 oneadder f0 (x[0],y[0],cin,s[0],c[0]);
 oneadder f1 (x[1],y[1],c[0],s[1],c[1]);
 oneadder f2 (x[2],y[2],c[1],s[2],c[2]);
 oneadder f3 (x[3],y[3],c[2],s[3],cout);
endmodule

tutorial1/mine_tb.v
// Verilog test bench for example_3_1
`timescale 1ns/100ps
`include "mine.v"

module mine_tb;

   wire A, B, C, D, E;
   integer k=0;

   assign {A,B,C} = k;
   mine the_circuit(A, B, C, D, E);

   initial begin

      $dumpfile("mine.vcd");
      $dumpvars(0, mine_tb);

      for (k=0; k<8; k=k+1)
        #10 $display("from mine done testing case %d", k);

      $finish;

   end

endmodule

tutorial1/mine.vcd
$date
	Wed Oct 31 17:50:16 2018
$end
$version
	Icarus Verilog
$end
$timescale
	100ps
$end
$scope module mine_tb $end
$var wire 1 ! A $end
$var wire 1 " B $end
$var wire 1 # C $end
$var wire 1 $ D $end
$var wire 1 % E $end
$var integer 32 & k [31:0] $end
$scope module the_circuit $end
$var wire 1 $ cin $end
$var wire 1 # cout $end
$var wire 4 ' s [3:0] $end
$var wire 4 ( x [3:0] $end
$var wire 4 ) y [3:0] $end
$scope module f0 $end
$var wire 1 * a $end
$var wire 1 + b $end
$var wire 1 $ c $end
$var wire 1 , cout $end
$var wire 1 - s $end
$var wire 1 . w1 $end
$var wire 1 / w2 $end
$var wire 1 0 w3 $end
$var wire 1 1 w4 $end
$upscope $end
$scope module f1 $end
$var wire 1 2 a $end
$var wire 1 3 b $end
$var wire 1 , c $end
$var wire 1 4 cout $end
$var wire 1 5 s $end
$var wire 1 6 w1 $end
$var wire 1 7 w2 $end
$var wire 1 8 w3 $end
$var wire 1 9 w4 $end
$upscope $end
$scope module f2 $end
$var wire 1 : a $end
$var wire 1 ; b $end
$var wire 1 4 c $end
$var wire 1 < cout $end
$var wire 1 = s $end
$var wire 1 > w1 $end
$var wire 1 ? w2 $end
$var wire 1 @ w3 $end
$var wire 1 A w4 $end
$upscope $end
$scope module f3 $end
$var wire 1 B a $end
$var wire 1 C b $end
$var wire 1 < c $end
$var wire 1 # cout $end
$var wire 1 D s $end
$var wire 1 E w1 $end
$var wire 1 F w2 $end
$var wire 1 G w3 $end
$var wire 1 H w4 $end
$upscope $end
$upscope $end
$upscope $end
$enddefinitions $end
#0
$dumpvars
zH
zG
zF
zE
xD
0C
0B
zA
z@
z?
z>
x=
x<
0;
0:
z9
z8
z7
z6
x5
x4
03
02
x1
x0
x/
x.
x-
x,
0+
z*
b0 )
b0z (
bx '
b0 &
z%
0$
x#
x"
0!
$end
#10
01
0/
00
0H
0G
0F
0E
0A
0@
0?
0>
09
08
07
06
#20
0,
0#
0<
04
#30
05
0D
0=
b0x '
#100
1$
b1 &
#110
x0
#120
x,
#130
x5
b0xx '
#200
0$
x#
b10 &
#210
00
#220
0,
#230
05
b0x '
#300
1$
b11 &
#310
x0
#320
x,
#330
x5
b0xx '
#400
0$
0#
b100 &
#410
00
#420
0,
#430
05
b0x '
#500
1$
b101 &
#510
x0
#520
x,
#530
x5
b0xx '
#600
0$
x#
b110 &
#610
00
#620
0,
#630
05
b0x '
#700
1$
b111 &
#710
x0
#720
x,
#730
x5
b0xx '
#800
1+
0$
0#
b1 )
1!
b1000 &
