mine/fourbitadder.v
module fulladder(a,b,c,s,cout);
input a,b,c;
output s,cout;
wire w1, w2, w3, w4, s, cout;

xor g1(w1, a, b);
xor g2(s, w1, c);
 and g3(w2, c, b);
 and g4(w3, c, a);
 and g5(w4, a, b);
or g6(cout, w2, w3, w4);

endmodule
module fourbitadder(x,y,s,cout,cin);
input [3:0] x,y;
output [3:0] s;
input cin;
output cout;
wire c[3:0];
 fulladder f0 (x[0],y[0],cin,s[0],c[0]);
 fulladder f1 (x[1],y[1],c[0],s[1],c[1]);
 fulladder f2 (x[2],y[2],c[1],s[2],c[2]);
 fulladder f3 (x[3],y[3],c[2],s[3],cout);
endmodule

mine/adder_tb.v
// Verilog test bench
`timescale 1ns/100ps
`include "fourbitadder.v"

module adder_tb;

wire A, B, C, D, E;
integer k=0;

assign {A,B,C,D} = k;
fourbitadder the_circuit(E, A, B, C, D);

   initial begin

      $dumpfile("fourbitadder.vcd");
      $dumpvars(0, adder_tb);

      for (k=0; k<8; k=k+1)
        #10 $display("adder testing case %d", k);

      $finish;

   end

endmodule

mine/fourbitadder.vcd
$date
	Fri Nov  2 17:33:57 2018
$end
$version
	Icarus Verilog
$end
$timescale
	100ps
$end
$scope module adder_tb $end
$var wire 1 ! A $end
$var wire 1 " B $end
$var wire 1 # C $end
$var wire 1 $ D $end
$var wire 1 % E $end
$var integer 32 & k [31:0] $end
$scope module the_circuit $end
$var wire 1 % cin $end
$var wire 1 $ cout $end
$var wire 4 ' s [3:0] $end
$var wire 4 ( x [3:0] $end
$var wire 4 ) y [3:0] $end
$scope module f0 $end
$var wire 1 * a $end
$var wire 1 + b $end
$var wire 1 % c $end
$var wire 1 , cout $end
$var wire 1 - s $end
$var wire 1 . w1 $end
$var wire 1 / w2 $end
$var wire 1 0 w3 $end
$var wire 1 1 w4 $end
$upscope $end
$scope module f1 $end
$var wire 1 2 a $end
$var wire 1 3 b $end
$var wire 1 , c $end
$var wire 1 4 cout $end
$var wire 1 5 s $end
$var wire 1 6 w1 $end
$var wire 1 7 w2 $end
$var wire 1 8 w3 $end
$var wire 1 9 w4 $end
$upscope $end
$scope module f2 $end
$var wire 1 : a $end
$var wire 1 ; b $end
$var wire 1 4 c $end
$var wire 1 < cout $end
$var wire 1 = s $end
$var wire 1 > w1 $end
$var wire 1 ? w2 $end
$var wire 1 @ w3 $end
$var wire 1 A w4 $end
$upscope $end
$scope module f3 $end
$var wire 1 B a $end
$var wire 1 C b $end
$var wire 1 < c $end
$var wire 1 $ cout $end
$var wire 1 D s $end
$var wire 1 E w1 $end
$var wire 1 F w2 $end
$var wire 1 G w3 $end
$var wire 1 H w4 $end
$upscope $end
$upscope $end
$upscope $end
$enddefinitions $end
#0
$dumpvars
0H
0G
0F
0E
0D
0C
0B
0A
0@
0?
0>
0=
0<
0;
0:
09
08
07
06
x5
04
03
02
01
00
x/
x.
x-
x,
z+
0*
b0z )
b0 (
b0xx '
b0 &
z%
0$
x#
z"
0!
$end
#100
x0
x1
1*
b1 (
1!
b1 &
#200
00
01
0*
b0 (
0!
b10 &
#300
x0
x1
1*
b1 (
1!
b11 &
#400
00
01
0*
b0 (
0!
b100 &
#500
x0
x1
1*
b1 (
1!
b101 &
#600
00
01
0*
b0 (
0!
b110 &
#700
x0
x1
1*
b1 (
1!
b111 &
#800
00
01
0*
b0 (
0!
b1000 &
